cgol/__init__.py
cgol/__main__.py
cgol/game.py
cgol/icon.png
cgol/parser.py
cgol/utils.py
cgol/world.py
CGOL-0.9.6.dist-info/LICENSE
CGOL-0.9.6.dist-info/METADATA
CGOL-0.9.6.dist-info/WHEEL
CGOL-0.9.6.dist-info/entry_points.txt
CGOL-0.9.6.dist-info/top_level.txt
CGOL-0.9.6.dist-info/RECORD
