Metadata-Version: 2.1
Name: CGOL
Version: 0.9.6
Summary: A whack Conway's Game of Life implementation.
Author-email: Neido <reg@neido.de>
Maintainer-email: Neido <reg@neido.de>
License: GPL-3
Project-URL: Homepage, https://github.com/INeido/CGOL/
Project-URL: Repository, https://github.com/INeido/CGOL/
Project-URL: Issues, https://github.com/INeido/CGOL/issues
Classifier: Programming Language :: Python :: 3
Classifier: Development Status :: 4 - Beta
Classifier: Intended Audience :: Science/Research
Classifier: Topic :: Games/Entertainment :: Simulation
Classifier: License :: OSI Approved :: GNU General Public License v3 (GPLv3)
Classifier: Operating System :: OS Independent
Classifier: Natural Language :: English
Requires-Python: >=3
License-File: LICENSE
Requires-Dist: pygame
Requires-Dist: numpy
